FIR.v
// file: FIR.v
// author: @bkhmsi

`timescale 1ns/1ns

module FIR(clk,rst,x,dataout);
input [7:0]x;
input clk,rst;
output [9:0]dataout;
wire [7:0]d1,d2,d3;
wire [7:0]m1,m2,m3,m4,m5;
wire [7:0]d11,d12,d13,d14;
parameter h0=3'b101;
parameter h1=3'b100;
parameter h2=3'b011;
parameter h3=3'b010;
parameter h4=3'b001;
assign m1=x>>h0;
DFF u2(clk,rst,x,d11);
assign m2=d11>>h1;
assign d1=m1+m2;
DFF u4(clk,rst,d11,d12);
assign m3=d12>>h2;
assign d2=d1+m3;
DFF u6(clk,rst,d12,d13);
assign m4=d13>>h3;
assign d3=d2+m4;
DFF u8(clk,rst,d13,d14);
assign m5=d14>>h4;
assign dataout=d3+m5;
endmodule

module DFF(clk,rst,d,q);// sub module d flipflop
input clk,rst;
input [7:0]d;
output [7:0]q;
reg [7:0]q;
always@(posedge clk) begin
    if(rst) q <=0;
    else q <=d;
end
endmodule

FIR_tb.v
// file: FIR_tb.v
// author: @bkhmsi
// Testbench for FIR

`timescale 1ns/1ns

module FIR_tb;

	//Inputs
	reg [7: 0] x;
	reg clk;
	reg rst;


	//Outputs
	wire [9: 0] dataout;

	//Instantiation of Unit Under Test
	FIR uut (
		.x(x),
		.clk(clk),
		.rst(rst),
		.dataout(dataout)
	);
	
	always #50 clk = ~clk;

	initial begin
	//Inputs initialization
    clk = 0;
    rst = 0;
    x = 0;
    #100;
    rst = 1;
    #100;
    rst = 0;
    x = 8'd5;
    #100;
    x = 8'd10;
    #100;
    x = 8'd12;
    #100;
    x = 8'd15;
    #100;
    x = 8'd16;
    #100;
	end
endmodule

simulation.vcd
$date
	Sun May 15 18:06:15 2016
$end
$version
	Icarus Verilog
$end
$timescale
	1ns
$end
$scope module FIR_tb $end
$var wire 10 ! dataout [9:0] $end
$var reg 1 " clk $end
$var reg 1 # rst $end
$var reg 8 $ x [7:0] $end
$scope module uut $end
$var wire 1 " clk $end
$var wire 1 # rst $end
$var wire 8 % x [7:0] $end
$var wire 8 & m5 [7:0] $end
$var wire 8 ' m4 [7:0] $end
$var wire 8 ( m3 [7:0] $end
$var wire 8 ) m2 [7:0] $end
$var wire 8 * m1 [7:0] $end
$var wire 10 + dataout [9:0] $end
$var wire 8 , d3 [7:0] $end
$var wire 8 - d2 [7:0] $end
$var wire 8 . d14 [7:0] $end
$var wire 8 / d13 [7:0] $end
$var wire 8 0 d12 [7:0] $end
$var wire 8 1 d11 [7:0] $end
$var wire 8 2 d1 [7:0] $end
$scope module u2 $end
$var wire 1 " clk $end
$var wire 8 3 d [7:0] $end
$var wire 1 # rst $end
$var reg 8 4 q [7:0] $end
$upscope $end
$scope module u4 $end
$var wire 1 " clk $end
$var wire 8 5 d [7:0] $end
$var wire 1 # rst $end
$var reg 8 6 q [7:0] $end
$upscope $end
$scope module u6 $end
$var wire 1 " clk $end
$var wire 8 7 d [7:0] $end
$var wire 1 # rst $end
$var reg 8 8 q [7:0] $end
$upscope $end
$scope module u8 $end
$var wire 1 " clk $end
$var wire 8 9 d [7:0] $end
$var wire 1 # rst $end
$var reg 8 : q [7:0] $end
$upscope $end
$upscope $end
$upscope $end
$enddefinitions $end
#0
$dumpvars
bx :
bx 9
bx 8
bx 7
bx 6
bx 5
bx 4
b0 3
bx 2
bx 1
bx 0
bx /
bx .
bx -
bx ,
bx +
b0 *
b0xxxx )
b0xxxxx (
b0xxxxxx '
b0xxxxxxx &
b0 %
b0 $
0#
0"
bx !
$end
#50
b0 2
b0 )
b0 1
b0 4
b0 5
1"
#100
0"
1#
#150
b0 !
b0 +
b0 &
b0 ,
b0 '
b0 -
b0 (
b0 .
b0 :
b0 /
b0 8
b0 9
b0 0
b0 6
b0 7
1"
#200
0"
b101 $
b101 %
b101 3
0#
#250
b101 1
b101 4
b101 5
1"
#300
0"
b1010 $
b1010 %
b1010 3
#350
b101 0
b101 6
b101 7
b1010 1
b1010 4
b1010 5
1"
#400
0"
b1100 $
b1100 %
b1100 3
#450
b1 -
b1 (
b10 !
b10 +
b10 ,
b1 '
b1100 1
b1100 4
b1100 5
b1010 0
b1010 6
b1010 7
b101 /
b101 8
b101 9
1"
#500
0"
b1111 $
b1111 %
b1111 3
#550
b10 &
b101 !
b101 +
b11 ,
b10 '
b101 .
b101 :
b1010 /
b1010 8
b1010 9
b1100 0
b1100 6
b1100 7
b1111 1
b1111 4
b1111 5
1"
#600
0"
b10000 $
b10000 %
b10000 3
#650
b10 -
b1 2
b1 )
b101 ,
b11 '
b1010 !
b1010 +
b101 &
b10000 1
b10000 4
b10000 5
b1111 0
b1111 6
b1111 7
b1100 /
b1100 8
b1100 9
b1010 .
b1010 :
1"
#700
0"
#750
b110 &
b1100 !
b1100 +
b110 ,
b11 -
b10 (
b1100 .
b1100 :
b1111 /
b1111 8
b1111 9
b10000 0
b10000 6
b10000 7
1"
#800
0"
#850
b111 ,
b100 '
b1110 !
b1110 +
b111 &
b10000 /
b10000 8
b10000 9
b1111 .
b1111 :
1"
#900
0"
#950
b1111 !
b1111 +
b1000 &
b10000 .
b10000 :
1"
